<?xml version="1.0"?>
<auctions><item><itemid>1</itemid><customerid>1</customerid><itemname>Nikon</itemname><category>Camera</category><description>New Camera</description><startdate>20/05/2015</startdate><starttime>20:07</starttime><enddate>30/05/2015</enddate><endtime>02:13</endtime><status>in_progress</status><bidprice>123.00</bidprice><reserveprice>1234.00</reserveprice><buyitnowprice>12345.00</buyitnowprice></item><item><itemid>2</itemid><customerid>1</customerid><itemname>Canon</itemname><category>Camera</category><description>Second Camera</description><startdate>20/05/2015</startdate><starttime>20:08</starttime><enddate>27/05/2015</enddate><endtime>00:15</endtime><status>in_progress</status><bidprice>1.00</bidprice><reserveprice>2.00</reserveprice><buyitnowprice>3.00</buyitnowprice></item><item><itemid>3</itemid><customerid>1</customerid><itemname>New Item</itemname><category>New Other Item</category><description>New other item added</description><startdate>20/05/2015</startdate><starttime>20:08</starttime><enddate>20/05/2015</enddate><endtime>21:10</endtime><status>in_progress</status><bidprice>5256.00</bidprice><reserveprice>3.00</reserveprice><buyitnowprice>4.00</buyitnowprice></item><item><itemid>4</itemid><customerid>1</customerid><itemname>Other Items</itemname><category>Other</category><description>New item</description><startdate>20/05/2015</startdate><starttime>20:09</starttime><enddate>25/05/2015</enddate><endtime>02:09</endtime><status>SOLD</status><bidprice>33.00</bidprice><reserveprice>2.00</reserveprice><buyitnowprice>33.00</buyitnowprice></item><item><itemid>5</itemid><customerid>1</customerid><itemname>HTC</itemname><category>Phone</category><description>New phone Htc One</description><startdate>20/05/2015</startdate><starttime>20:09</starttime><enddate>25/05/2015</enddate><endtime>20:10</endtime><status>in_progress</status><bidprice>2367.00</bidprice><reserveprice>2312.00</reserveprice><buyitnowprice>3145.00</buyitnowprice></item><item><itemid>6</itemid><customerid>1</customerid><itemname>Iphone 5c</itemname><category>Phone</category><description>New Phone</description><startdate>20/05/2015</startdate><starttime>20:10</starttime><enddate>25/05/2015</enddate><endtime>01:14</endtime><status>SOLD</status><bidprice>233.00</bidprice><reserveprice>32.00</reserveprice><buyitnowprice>233.00</buyitnowprice></item></auctions>
